{"status":"Eindstand","publicatie_datum_tijd":"2023-11-23T00:52:39+01:00","gemeente":{"naam":"Nieuwegein","cbs_code":"G0356","provincie":{"code":"UT","naam":"Utrecht","aantal_inwoners":1387657},"kieskring":"Utrecht","aantal_inwoners":65437},"huidige_verkiezing":{"verkiezing_code":"TK23","kiesgerechtigden":49902,"zetels":null,"opkomst":37847,"opkomst_promillage":758,"ongeldig":100,"ongeldig_promillage":2,"blanco":85,"blanco_promillage":2},"vorige_verkiezing":{"verkiezing_code":"TK21","kiesgerechtigden":49306,"zetels":null,"opkomst":37438,"opkomst_promillage":759,"ongeldig":72,"ongeldig_promillage":1,"blanco":72,"blanco_promillage":1},"partijen":[{"partij":{"name":"Nederland met een PLAN","short_name":"NLPLAN"},"huidig":{"verkiezing_code":"TK23","stemmen":30,"stemmen_promillage":1,"zetels":null},"vorig":{"verkiezing_code":"TK21","stemmen":0,"stemmen_promillage":0,"zetels":null}},{"partij":{"name":"SP (Socialistische Partij)","short_name":"SP"},"huidig":{"verkiezing_code":"TK23","stemmen":1429,"stemmen_promillage":38,"zetels":null},"vorig":{"verkiezing_code":"TK21","stemmen":2457,"stemmen_promillage":66,"zetels":null}},{"partij":{"name":"VVD","short_name":"VVD"},"huidig":{"verkiezing_code":"TK23","stemmen":5926,"stemmen_promillage":157,"zetels":null},"vorig":{"verkiezing_code":"TK21","stemmen":9078,"stemmen_promillage":243,"zetels":null}},{"partij":{"name":"DENK","short_name":"DENK"},"huidig":{"verkiezing_code":"TK23","stemmen":1224,"stemmen_promillage":32,"zetels":null},"vorig":{"verkiezing_code":"TK21","stemmen":856,"stemmen_promillage":23,"zetels":null}},{"partij":{"name":"JA21","short_name":"JA21"},"huidig":{"verkiezing_code":"TK23","stemmen":246,"stemmen_promillage":7,"zetels":null},"vorig":{"verkiezing_code":"TK21","stemmen":924,"stemmen_promillage":25,"zetels":null}},{"partij":{"name":"LP (Libertaire Partij)","short_name":"LP"},"huidig":{"verkiezing_code":"TK23","stemmen":17,"stemmen_promillage":0,"zetels":null},"vorig":{"verkiezing_code":"TK21","stemmen":27,"stemmen_promillage":1,"zetels":null}},{"partij":{"name":"Overige 2021","short_name":"OVERIG"},"huidig":{"verkiezing_code":"TK23","stemmen":0,"stemmen_promillage":0,"zetels":null},"vorig":{"verkiezing_code":"TK21","stemmen":591,"stemmen_promillage":16,"zetels":null}},{"partij":{"name":"Staatkundig Gereformeerde Partij (SGP)","short_name":"SGP"},"huidig":{"verkiezing_code":"TK23","stemmen":222,"stemmen_promillage":6,"zetels":null},"vorig":{"verkiezing_code":"TK21","stemmen":208,"stemmen_promillage":6,"zetels":null}},{"partij":{"name":"ChristenUnie","short_name":"CU"},"huidig":{"verkiezing_code":"TK23","stemmen":584,"stemmen_promillage":16,"zetels":null},"vorig":{"verkiezing_code":"TK21","stemmen":995,"stemmen_promillage":27,"zetels":null}},{"partij":{"name":"Piratenpartij - De Groenen","short_name":"PIRGRO"},"huidig":{"verkiezing_code":"TK23","stemmen":50,"stemmen_promillage":1,"zetels":null},"vorig":{"verkiezing_code":"TK21","stemmen":109,"stemmen_promillage":3,"zetels":null}},{"partij":{"name":"BBB","short_name":"BBB"},"huidig":{"verkiezing_code":"TK23","stemmen":867,"stemmen_promillage":23,"zetels":null},"vorig":{"verkiezing_code":"TK21","stemmen":94,"stemmen_promillage":3,"zetels":null}},{"partij":{"name":"BVNL / Groep Van Haga","short_name":"BVNL"},"huidig":{"verkiezing_code":"TK23","stemmen":162,"stemmen_promillage":4,"zetels":null},"vorig":{"verkiezing_code":"TK21","stemmen":0,"stemmen_promillage":0,"zetels":null}},{"partij":{"name":"Samen voor Nederland","short_name":"SAMEN"},"huidig":{"verkiezing_code":"TK23","stemmen":21,"stemmen_promillage":1,"zetels":null},"vorig":{"verkiezing_code":"TK21","stemmen":0,"stemmen_promillage":0,"zetels":null}},{"partij":{"name":"D66","short_name":"D66"},"huidig":{"verkiezing_code":"TK23","stemmen":2223,"stemmen_promillage":59,"zetels":null},"vorig":{"verkiezing_code":"TK21","stemmen":5376,"stemmen_promillage":144,"zetels":null}},{"partij":{"name":"PartijvdSport","short_name":"PVDSPO"},"huidig":{"verkiezing_code":"TK23","stemmen":24,"stemmen_promillage":1,"zetels":null},"vorig":{"verkiezing_code":"TK21","stemmen":0,"stemmen_promillage":0,"zetels":null}},{"partij":{"name":"Forum voor Democratie","short_name":"FVD"},"huidig":{"verkiezing_code":"TK23","stemmen":922,"stemmen_promillage":24,"zetels":null},"vorig":{"verkiezing_code":"TK21","stemmen":1731,"stemmen_promillage":46,"zetels":null}},{"partij":{"name":"Volt","short_name":"VOLT"},"huidig":{"verkiezing_code":"TK23","stemmen":605,"stemmen_promillage":16,"zetels":null},"vorig":{"verkiezing_code":"TK21","stemmen":750,"stemmen_promillage":20,"zetels":null}},{"partij":{"name":"BIJ1","short_name":"BIJ1"},"huidig":{"verkiezing_code":"TK23","stemmen":176,"stemmen_promillage":5,"zetels":null},"vorig":{"verkiezing_code":"TK21","stemmen":352,"stemmen_promillage":9,"zetels":null}},{"partij":{"name":"50PLUS","short_name":"50PLUS"},"huidig":{"verkiezing_code":"TK23","stemmen":250,"stemmen_promillage":7,"zetels":null},"vorig":{"verkiezing_code":"TK21","stemmen":575,"stemmen_promillage":15,"zetels":null}},{"partij":{"name":"PVV (Partij voor de Vrijheid)","short_name":"PVV"},"huidig":{"verkiezing_code":"TK23","stemmen":10292,"stemmen_promillage":273,"zetels":null},"vorig":{"verkiezing_code":"TK21","stemmen":4551,"stemmen_promillage":122,"zetels":null}},{"partij":{"name":"LEF - Voor de Nieuwe Generatie","short_name":"LEF"},"huidig":{"verkiezing_code":"TK23","stemmen":15,"stemmen_promillage":0,"zetels":null},"vorig":{"verkiezing_code":"TK21","stemmen":0,"stemmen_promillage":0,"zetels":null}},{"partij":{"name":"GROENLINKS / Partij van de Arbeid (PvdA)","short_name":"GLPVDA"},"huidig":{"verkiezing_code":"TK23","stemmen":5840,"stemmen_promillage":155,"zetels":null},"vorig":{"verkiezing_code":"TK21","stemmen":4189,"stemmen_promillage":112,"zetels":null}},{"partij":{"name":"CDA","short_name":"CDA"},"huidig":{"verkiezing_code":"TK23","stemmen":977,"stemmen_promillage":26,"zetels":null},"vorig":{"verkiezing_code":"TK21","stemmen":2900,"stemmen_promillage":78,"zetels":null}},{"partij":{"name":"Politieke Partij voor Basisinkomen","short_name":"PPBINK"},"huidig":{"verkiezing_code":"TK23","stemmen":11,"stemmen_promillage":0,"zetels":null},"vorig":{"verkiezing_code":"TK21","stemmen":0,"stemmen_promillage":0,"zetels":null}},{"partij":{"name":"Partij voor de Dieren","short_name":"PVDD"},"huidig":{"verkiezing_code":"TK23","stemmen":804,"stemmen_promillage":21,"zetels":null},"vorig":{"verkiezing_code":"TK21","stemmen":1408,"stemmen_promillage":38,"zetels":null}},{"partij":{"name":"Splinter","short_name":"SPLINTER"},"huidig":{"verkiezing_code":"TK23","stemmen":54,"stemmen_promillage":1,"zetels":null},"vorig":{"verkiezing_code":"TK21","stemmen":123,"stemmen_promillage":3,"zetels":null}},{"partij":{"name":"Nieuw Sociaal Contract","short_name":"NSC"},"huidig":{"verkiezing_code":"TK23","stemmen":4650,"stemmen_promillage":123,"zetels":null},"vorig":{"verkiezing_code":"TK21","stemmen":0,"stemmen_promillage":0,"zetels":null}}]}