{"status":"Eindstand","publicatie_datum_tijd":"2023-11-23T01:26:13+01:00","gemeente":{"naam":"Woerden","cbs_code":"G0632","provincie":{"code":"UT","naam":"Utrecht","aantal_inwoners":1387657},"kieskring":"Utrecht","aantal_inwoners":53237},"huidige_verkiezing":{"verkiezing_code":"TK23","kiesgerechtigden":40860,"zetels":null,"opkomst":33999,"opkomst_promillage":832,"ongeldig":50,"ongeldig_promillage":1,"blanco":59,"blanco_promillage":1},"vorige_verkiezing":{"verkiezing_code":"TK21","kiesgerechtigden":40201,"zetels":null,"opkomst":34121,"opkomst_promillage":849,"ongeldig":37,"ongeldig_promillage":1,"blanco":59,"blanco_promillage":1},"partijen":[{"partij":{"name":"Splinter","short_name":"SPLINTER"},"huidig":{"verkiezing_code":"TK23","stemmen":108,"stemmen_promillage":3,"zetels":null},"vorig":{"verkiezing_code":"TK21","stemmen":139,"stemmen_promillage":4,"zetels":null}},{"partij":{"name":"PartijvdSport","short_name":"PVDSPO"},"huidig":{"verkiezing_code":"TK23","stemmen":17,"stemmen_promillage":1,"zetels":null},"vorig":{"verkiezing_code":"TK21","stemmen":0,"stemmen_promillage":0,"zetels":null}},{"partij":{"name":"Overige 2021","short_name":"OVERIG"},"huidig":{"verkiezing_code":"TK23","stemmen":0,"stemmen_promillage":0,"zetels":null},"vorig":{"verkiezing_code":"TK21","stemmen":436,"stemmen_promillage":13,"zetels":null}},{"partij":{"name":"Partij voor de Dieren","short_name":"PVDD"},"huidig":{"verkiezing_code":"TK23","stemmen":619,"stemmen_promillage":18,"zetels":null},"vorig":{"verkiezing_code":"TK21","stemmen":1039,"stemmen_promillage":31,"zetels":null}},{"partij":{"name":"PVV (Partij voor de Vrijheid)","short_name":"PVV"},"huidig":{"verkiezing_code":"TK23","stemmen":6382,"stemmen_promillage":188,"zetels":null},"vorig":{"verkiezing_code":"TK21","stemmen":2651,"stemmen_promillage":78,"zetels":null}},{"partij":{"name":"ChristenUnie","short_name":"CU"},"huidig":{"verkiezing_code":"TK23","stemmen":1200,"stemmen_promillage":35,"zetels":null},"vorig":{"verkiezing_code":"TK21","stemmen":1885,"stemmen_promillage":55,"zetels":null}},{"partij":{"name":"Nederland met een PLAN","short_name":"NLPLAN"},"huidig":{"verkiezing_code":"TK23","stemmen":12,"stemmen_promillage":0,"zetels":null},"vorig":{"verkiezing_code":"TK21","stemmen":0,"stemmen_promillage":0,"zetels":null}},{"partij":{"name":"Forum voor Democratie","short_name":"FVD"},"huidig":{"verkiezing_code":"TK23","stemmen":638,"stemmen_promillage":19,"zetels":null},"vorig":{"verkiezing_code":"TK21","stemmen":1209,"stemmen_promillage":36,"zetels":null}},{"partij":{"name":"Politieke Partij voor Basisinkomen","short_name":"PPBINK"},"huidig":{"verkiezing_code":"TK23","stemmen":3,"stemmen_promillage":0,"zetels":null},"vorig":{"verkiezing_code":"TK21","stemmen":0,"stemmen_promillage":0,"zetels":null}},{"partij":{"name":"Nieuw Sociaal Contract","short_name":"NSC"},"huidig":{"verkiezing_code":"TK23","stemmen":4154,"stemmen_promillage":123,"zetels":null},"vorig":{"verkiezing_code":"TK21","stemmen":0,"stemmen_promillage":0,"zetels":null}},{"partij":{"name":"CDA","short_name":"CDA"},"huidig":{"verkiezing_code":"TK23","stemmen":1827,"stemmen_promillage":54,"zetels":null},"vorig":{"verkiezing_code":"TK21","stemmen":4219,"stemmen_promillage":124,"zetels":null}},{"partij":{"name":"Samen voor Nederland","short_name":"SAMEN"},"huidig":{"verkiezing_code":"TK23","stemmen":13,"stemmen_promillage":0,"zetels":null},"vorig":{"verkiezing_code":"TK21","stemmen":0,"stemmen_promillage":0,"zetels":null}},{"partij":{"name":"GROENLINKS / Partij van de Arbeid (PvdA)","short_name":"GLPVDA"},"huidig":{"verkiezing_code":"TK23","stemmen":4803,"stemmen_promillage":142,"zetels":null},"vorig":{"verkiezing_code":"TK21","stemmen":2931,"stemmen_promillage":86,"zetels":null}},{"partij":{"name":"BVNL / Groep Van Haga","short_name":"BVNL"},"huidig":{"verkiezing_code":"TK23","stemmen":148,"stemmen_promillage":4,"zetels":null},"vorig":{"verkiezing_code":"TK21","stemmen":0,"stemmen_promillage":0,"zetels":null}},{"partij":{"name":"Staatkundig Gereformeerde Partij (SGP)","short_name":"SGP"},"huidig":{"verkiezing_code":"TK23","stemmen":1180,"stemmen_promillage":35,"zetels":null},"vorig":{"verkiezing_code":"TK21","stemmen":1133,"stemmen_promillage":33,"zetels":null}},{"partij":{"name":"LP (Libertaire Partij)","short_name":"LP"},"huidig":{"verkiezing_code":"TK23","stemmen":20,"stemmen_promillage":1,"zetels":null},"vorig":{"verkiezing_code":"TK21","stemmen":7,"stemmen_promillage":0,"zetels":null}},{"partij":{"name":"SP (Socialistische Partij)","short_name":"SP"},"huidig":{"verkiezing_code":"TK23","stemmen":720,"stemmen_promillage":21,"zetels":null},"vorig":{"verkiezing_code":"TK21","stemmen":1198,"stemmen_promillage":35,"zetels":null}},{"partij":{"name":"Piratenpartij - De Groenen","short_name":"PIRGRO"},"huidig":{"verkiezing_code":"TK23","stemmen":27,"stemmen_promillage":1,"zetels":null},"vorig":{"verkiezing_code":"TK21","stemmen":55,"stemmen_promillage":2,"zetels":null}},{"partij":{"name":"VVD","short_name":"VVD"},"huidig":{"verkiezing_code":"TK23","stemmen":6320,"stemmen_promillage":186,"zetels":null},"vorig":{"verkiezing_code":"TK21","stemmen":8614,"stemmen_promillage":253,"zetels":null}},{"partij":{"name":"LEF - Voor de Nieuwe Generatie","short_name":"LEF"},"huidig":{"verkiezing_code":"TK23","stemmen":10,"stemmen_promillage":0,"zetels":null},"vorig":{"verkiezing_code":"TK21","stemmen":0,"stemmen_promillage":0,"zetels":null}},{"partij":{"name":"JA21","short_name":"JA21"},"huidig":{"verkiezing_code":"TK23","stemmen":242,"stemmen_promillage":7,"zetels":null},"vorig":{"verkiezing_code":"TK21","stemmen":913,"stemmen_promillage":27,"zetels":null}},{"partij":{"name":"Volt","short_name":"VOLT"},"huidig":{"verkiezing_code":"TK23","stemmen":616,"stemmen_promillage":18,"zetels":null},"vorig":{"verkiezing_code":"TK21","stemmen":766,"stemmen_promillage":23,"zetels":null}},{"partij":{"name":"D66","short_name":"D66"},"huidig":{"verkiezing_code":"TK23","stemmen":2443,"stemmen_promillage":72,"zetels":null},"vorig":{"verkiezing_code":"TK21","stemmen":5436,"stemmen_promillage":160,"zetels":null}},{"partij":{"name":"BIJ1","short_name":"BIJ1"},"huidig":{"verkiezing_code":"TK23","stemmen":84,"stemmen_promillage":2,"zetels":null},"vorig":{"verkiezing_code":"TK21","stemmen":132,"stemmen_promillage":4,"zetels":null}},{"partij":{"name":"50PLUS","short_name":"50PLUS"},"huidig":{"verkiezing_code":"TK23","stemmen":169,"stemmen_promillage":5,"zetels":null},"vorig":{"verkiezing_code":"TK21","stemmen":507,"stemmen_promillage":15,"zetels":null}},{"partij":{"name":"DENK","short_name":"DENK"},"huidig":{"verkiezing_code":"TK23","stemmen":586,"stemmen_promillage":17,"zetels":null},"vorig":{"verkiezing_code":"TK21","stemmen":489,"stemmen_promillage":14,"zetels":null}},{"partij":{"name":"BBB","short_name":"BBB"},"huidig":{"verkiezing_code":"TK23","stemmen":1549,"stemmen_promillage":46,"zetels":null},"vorig":{"verkiezing_code":"TK21","stemmen":266,"stemmen_promillage":8,"zetels":null}}]}